django_affiliate_system/__init__.py
django_affiliate_system/__version__.py
django_affiliate_system/admin.py
django_affiliate_system/apps.py
django_affiliate_system/authentication.py
django_affiliate_system/config.py
django_affiliate_system/middleware.py
django_affiliate_system/models.py
django_affiliate_system/permissions.py
django_affiliate_system/serializers.py
django_affiliate_system/signals.py
django_affiliate_system/tasks.py
django_affiliate_system/tests.py
django_affiliate_system/urls.py
django_affiliate_system/utils.py
django_affiliate_system/views.py
django_affiliate_system/migrations/0001_initial.py
django_affiliate_system/migrations/0002_alter_commissionrule_options_and_more.py
django_affiliate_system/migrations/0003_add_affiliate_to_referralaction.py
django_affiliate_system/migrations/0004_populate_affiliate_field.py
django_affiliate_system/migrations/0005_make_affiliate_required.py
django_affiliate_system/migrations/0006_remove_referralaction_affiliates__tenant__cb1abf_idx_and_more.py
django_affiliate_system/migrations/__init__.py
django_affiliate_system/services/__init__.py
django_affiliate_system/services/commision.py
django_affiliate_system/services/tracking.py
django_affiliate_system/tests/conftest.py
django_affiliate_system-0.1.0a6.dist-info/licenses/LICENSE
example_project/manage.py
example_project/example_project/__init__.py
example_project/example_project/asgi.py
example_project/example_project/settings.py
example_project/example_project/urls.py
example_project/example_project/wsgi.py
django_affiliate_system-0.1.0a6.dist-info/METADATA
django_affiliate_system-0.1.0a6.dist-info/WHEEL
django_affiliate_system-0.1.0a6.dist-info/top_level.txt
django_affiliate_system-0.1.0a6.dist-info/RECORD
