Metadata-Version: 2.4
Name: django-affiliate-system
Version: 0.1.0a6
Summary: A comprehensive Django affiliate marketing and referral tracking system
Author-email: Ayodeji Akenroye <aayodeji.f@gmail.com>
License: MIT
Project-URL: Homepage, https://github.com/aayodejii/django-affiliate-system
Project-URL: Documentation, https://django-affiliate-system.readthedocs.io/
Project-URL: Repository, https://github.com/aayodejii/django-affiliate-system
Project-URL: Bug Reports, https://github.com/aayodejii/django-affiliate-system/issues
Keywords: django,affiliate,referral,tracking,commission,marketing
Classifier: Development Status :: 3 - Alpha
Classifier: Environment :: Web Environment
Classifier: Framework :: Django
Classifier: Framework :: Django :: 4.0
Classifier: Framework :: Django :: 4.1
Classifier: Framework :: Django :: 4.2
Classifier: Framework :: Django :: 5.0
Classifier: Intended Audience :: Developers
Classifier: License :: OSI Approved :: MIT License
Classifier: Operating System :: OS Independent
Classifier: Programming Language :: Python
Classifier: Programming Language :: Python :: 3
Classifier: Programming Language :: Python :: 3.9
Classifier: Programming Language :: Python :: 3.10
Classifier: Programming Language :: Python :: 3.11
Classifier: Programming Language :: Python :: 3.12
Classifier: Topic :: Internet :: WWW/HTTP
Classifier: Topic :: Internet :: WWW/HTTP :: Dynamic Content
Classifier: Topic :: Office/Business :: Financial
Classifier: Topic :: Software Development :: Libraries :: Python Modules
Requires-Python: >=3.9
License-File: LICENSE
Requires-Dist: Django<5.3,>=4.0
Requires-Dist: djangorestframework>=3.14.0
Requires-Dist: djangorestframework-simplejwt>=5.2.0
Provides-Extra: celery
Requires-Dist: celery>=5.2.0; extra == "celery"
Requires-Dist: redis>=4.5.0; extra == "celery"
Provides-Extra: dev
Requires-Dist: pytest>=7.0.0; extra == "dev"
Requires-Dist: pytest-django>=4.5.0; extra == "dev"
Requires-Dist: pytest-cov>=4.0.0; extra == "dev"
Requires-Dist: pytest-mock>=3.10.0; extra == "dev"
Requires-Dist: black>=23.0.0; extra == "dev"
Requires-Dist: flake8>=6.0.0; extra == "dev"
Requires-Dist: isort>=5.12.0; extra == "dev"
Requires-Dist: mypy>=1.0.0; extra == "dev"
Requires-Dist: django-stubs>=4.0.0; extra == "dev"
Requires-Dist: djangorestframework-stubs>=3.14.0; extra == "dev"
Requires-Dist: tox>=4.0.0; extra == "dev"
Requires-Dist: twine>=4.0.0; extra == "dev"
Requires-Dist: wheel>=0.40.0; extra == "dev"
Requires-Dist: build>=0.10.0; extra == "dev"
Requires-Dist: coverage>=7.0.0; extra == "dev"
Requires-Dist: factory-boy>=3.2.0; extra == "dev"
Requires-Dist: faker>=18.0.0; extra == "dev"
Provides-Extra: all
Requires-Dist: celery>=5.2.0; extra == "all"
Requires-Dist: redis>=4.5.0; extra == "all"
Dynamic: license-file
